chinese_keybert/__init__.py
chinese_keybert/core.py
chinese_keybert/ranking_functions.py
chinese_keybert/stopwords.py
chinese_keybert-0.1.0.dist-info/LICENSE
chinese_keybert-0.1.0.dist-info/METADATA
chinese_keybert-0.1.0.dist-info/WHEEL
chinese_keybert-0.1.0.dist-info/top_level.txt
chinese_keybert-0.1.0.dist-info/RECORD
