Metadata-Version: 2.1
Name: chinese-keybert
Version: 0.1.0
Summary: Chinese keyword extraction using transformer-based language models
Home-page: https://github.com/JacksonCakes/chinese_keybert
Author: Jaackson Cakes
Author-email: jacksonkek257@gmail.com
License: UNKNOWN
Platform: UNKNOWN
Classifier: Programming Language :: Python :: 3
Classifier: Programming Language :: Python :: 3.6
Classifier: Programming Language :: Python :: 3.7
Classifier: Programming Language :: Python :: 3.8
Classifier: Programming Language :: Python :: 3.9
Classifier: Programming Language :: Python :: 3.10
Classifier: License :: OSI Approved :: MIT License
Classifier: Operating System :: OS Independent
Classifier: Intended Audience :: Developers
Classifier: Intended Audience :: Science/Research
Classifier: Topic :: Scientific/Engineering :: Artificial Intelligence
Requires-Python: >=3.6
Requires-Dist: ckip-transformers (>=0.3.2)
Requires-Dist: numpy (>=1.20.1)
Requires-Dist: sentence-transformers (>=2.2.2)
